pygame_animation/__init__.py
pygame_animation/animation_manager.py
pygame_animation/smooth_animation.py
pygame_animation/smoothing_interface.py
pygame_animation/smoothing_methods.py
pygame_animation/target_manager.py
pygame_animation-1.0.0.dist-info/METADATA
pygame_animation-1.0.0.dist-info/WHEEL
pygame_animation-1.0.0.dist-info/top_level.txt
pygame_animation-1.0.0.dist-info/RECORD
