Metadata-Version: 2.1
Name: pygame_animation
Version: 1.0.0
Summary: A package for managing animations of pygame surfaces
Home-page: https://github.com/FrickTzy/Pygame-Animation
Author: FrickTzy (Kurt Arnoco)
License: UNKNOWN
Keywords: python,pygame,python game,python game development,pygame animations,python animations,pygame animation
Platform: UNKNOWN
